Workbook

Sheet Summary
B2: TMRW House of Brands — Portfolio Profitability Diagnostic
B3: Business Analyst case study | FY25 (year ended 31 Mar 2025) brand-level financials, sourced from RoC filings
B5: The Problem
B6: TMRW's brands are growing fast — Q1 FY26 revenue was up 38% YoY to Rs 197 Cr — but EBITDA losses grew even faster (Rs 63 Cr vs Rs 46 Cr a year ago). Every brand is chasing growth through discounts, ad spend and new stores, but not every brand is worth scaling at the same intensity. This model classifies TMRW's four disclosed D2C brands by growth vs. profitability trend, and models one reallocation scenario to show the path to portfolio breakeven.
B10: Portfolio 2x2: Growth vs. Profitability Trend (FY25 vs FY24)
B11: Brand | C11: Revenue Growth YoY | D11: EBITDA Margin (FY25) | E11: Net Loss Trend YoY | F11: Classification
B12: The Indian Garage Co (TIGC) | C12: ='Brand Financials'!E6 -> 1.0098522 | D12: ='Brand Financials'!F6 -> -0.0637 | E12: ='Brand Financials'!I6 -> -3.6 | F12: Scale
B13: Bewakoof | C13: ='Brand Financials'!E12 -> 0.075201989 | D13: ='Brand Financials'!F12 -> -0.34 | E13: ='Brand Financials'!I12 -> 0.2900097 | F13: Fix
B14: Wrogn | C14: ='Brand Financials'!E18 -> -0.090093763 | D14: ='Brand Financials'!F18 -> -0.275 | E14: ='Brand Financials'!I18 -> -0.32922535 | F14: Cut / Harvest
B15: Nobero* | C15: n/a (unofficial est. only) | D15: n/a | E15: n/a | F15: Watch (data-limited)
B17: *Nobero has no RoC-filed FY25 statement publicly available yet. Third-party e-commerce trackers estimate ~$60M (~Rs 500 Cr) GMV in 2025, growing 75-80% YoY - GMV is not comparable to the other brands' audited operating revenue, so it is excluded from the ranked model and flagged as a research gap.
B19: Headline Recommendation
B20: 1) SCALE - TIGC: revenue doubled (+101%) with an EBITDA margin of only -6.4%, the closest to breakeven of any brand. It deserves the next round of marketing and offline capex. 2) FIX - Bewakoof: revenue nearly flat (+8%) but losses fell 29% purely from cost discipline. Hold spend, keep tightening opex, don't chase growth yet. 3) CUT/HARVEST - Wrogn: second straight year of revenue decline (-9%) while losses grew 32% and accumulated losses hit Rs 709 Cr. Ad spend rose 63% while sales fell - that spend is not converting. Recommend freezing performance-marketing spend and re-underwriting the brand before any further capital. 4) INVESTIGATE - Nobero: claimed high growth but no audited financials on record. Get real numbers before allocating capital here.

Sheet Brand Financials
A1: Brand-Level Financials - FY24 vs FY25 (Rs Crore, RoC filings)
A3: Brand | C3: Revenue FY24 | D3: Revenue FY25 | E3: Growth YoY | F3: EBITDA Margin FY25 | G3: Net Loss FY24 | H3: Net Loss FY25 | I3: Loss Change YoY | K3: Source
A6: The Indian Garage Co (TIGC) | C6: 101.5 | D6: 204 | E6: =(D6-C6)/C6 -> 1.0098522 | F6: -0.0637 | G6: -5 | H6: -23 | I6: =(H6-G6)/ABS(G6) -> -3.6 | K6: Entrackr, 15 Jan 2026, RoC filings - revenue doubled, EBITDA margin -6.37%, flipped from Rs 5 Cr profit (FY24) to Rs 23 Cr net loss (FY25) as material costs +142%, job-work costs +193%
A12: Bewakoof | C12: 160.9 | D12: 173 | E12: =(D12-C12)/C12 -> 0.075201989 | F12: -0.34 | G12: -103.1 | H12: -73.2 | I12: =(H12-G12)/ABS(G12) -> 0.2900097 | K12: Inc42, 31 Oct 2025, RoC filings - EBITDA loss improved 38% to Rs 57 Cr (margin -34%, up from -59% in FY24); ad spend held flat at Rs 48.6 Cr; cost per Rs 1 revenue improved from Rs 1.65 to Rs 1.43
A18: Wrogn | C18: 245.3 | D18: 223.2 | E18: =(D18-C18)/C18 -> -0.090093763 | F18: -0.275 | G18: -56.8 | H18: -75.5 | I18: =(H18-G18)/ABS(G18) -> -0.32922535 | K18: Inc42 / Entrackr, 25 Sep 2025, RoC filings - 2nd consecutive year of revenue decline (-29% in FY24, -9% in FY25); ad spend +63% YoY despite falling sales; accumulated losses Rs 709 Cr; ROCE -70%
A24: Nobero - no RoC-filed FY25 statement located. Third-party estimate (ECDB, e-commerce GMV tracker): ~$60M (~Rs 500 Cr) GMV in 2025, +75-80% YoY. GMV is not audited revenue; excluded from ranked comparison above.
A26: TMRW consolidated (all brands): Q1 FY26 revenue Rs 197 Cr (+38% YoY), EBITDA loss Rs 63 Cr (vs Rs 46 Cr in Q1 FY25). Source: Mint / VentureIntelligence, Aug 2025 ServiceNow Ventures funding announcement.

Sheet 2x2 Scoring
A1: Classification Logic
A3: Axis 1: Revenue growth YoY (FY25 vs FY24) - is the brand actually getting bigger? Axis 2: EBITDA margin - how loss-making is each rupee of revenue right now? A brand that is growing AND has the best margin in the portfolio = Scale. Flat/slow growth but margin improving from cost control = Fix. Declining revenue AND worsening losses = Cut/Harvest.
A6: Brand | B6: Revenue Growth YoY | C6: EBITDA Margin FY25 | D6: Quadrant | E6: Rationale
A7: The Indian Garage Co | B7: ='Brand Financials'!E6 -> 1.0098522 | C7: ='Brand Financials'!F6 -> -0.0637 | D7: Scale | E7: High growth (+101%) + best-in-portfolio margin (-6.4%) = closest to profitable scale
A8: Bewakoof | B8: ='Brand Financials'!E12 -> 0.075201989 | C8: ='Brand Financials'!F12 -> -0.34 | D8: Fix | E8: Low growth (+8%) but margin improved 2,500 bps YoY via cost control - protect the improvement, don't overspend to chase growth yet
A9: Wrogn | B9: ='Brand Financials'!E18 -> -0.090093763 | C9: ='Brand Financials'!F18 -> -0.275 | D9: Cut / Harvest | E9: Revenue down 2 years running, margin worsening, ad spend up 63% without a sales response - capital is not converting

Sheet Recommendation Model
A1: Scenario: Reallocate Wrogn's Incremental Ad Spend to TIGC
A3: Wrogn's ad/promo spend rose 63% YoY in FY25 while revenue fell 9% - that spend did not convert. TIGC's EBITDA margin (-6.4%) is far closer to breakeven than Wrogn's (-27.5%). This scenario models freezing Wrogn's incremental ad spend and redeploying it into TIGC's proven, closer-to-breakeven growth engine, holding TIGC's FY25 EBITDA margin constant on the added revenue.
A7: Key Assumptions (editable - blue cells on yellow fill)
A8: Wrogn FY25 ad/promo spend (Rs Cr) | B8: 65 | D8: Approx. - Entrackr reports ad spend +63% YoY; this sets an FY25 level consistent with that increase
A9: Wrogn FY24 ad/promo spend (Rs Cr) | B9: 40 | D9: Implied base before the 63% YoY increase - i.e. the last year ad spend still roughly matched revenue
A10: TIGC revenue generated per Rs 1 of incremental ad spend (assumed) | B10: 8 | D10: Placeholder - TIGC does not disclose ad spend separately; assumes similar efficiency to its FY25 revenue-doubling performance. Flag this explicitly as an assumption when presenting.
A11: TIGC FY25 EBITDA margin | B11: -0.0637 | D11: From Brand Financials tab - held constant on incremental revenue for this scenario
A14: Reallocatable spend | B14: =B8-B9 -> 25
A16: Projected Impact
A17: Incremental TIGC revenue from reallocated spend (Rs Cr) | B17: =B14*B10 -> 200
A18: Incremental TIGC EBITDA impact (Rs Cr) | B18: =B17*B11 -> -12.74
A19: Wrogn EBITDA impact of freezing incremental spend (Rs Cr; spend removed = loss avoided 1:1) | B19: =B14 -> 25
A20: Net portfolio EBITDA improvement vs. FY25 base (Rs Cr) | B20: =B18+B19 -> 12.26
A22: Read: this is a directional model, not an audited forecast - TIGC's ad-spend efficiency is assumed, not disclosed. The purpose is to show the mechanism (redeploy capital from a brand where spend isn't converting to one where it is) and give a reader a number to react to, not a precise P&L. In a real engagement, the next step would be requesting TIGC's actual CAC / marketing-efficiency data before committing budget.

Sheet Sources
A1: Source | B1: Detail
A2: TMRW / ServiceNow Ventures | B2: Mint via VentureIntelligence, Aug 2025 - TMRW raised Rs 437 Cr from ServiceNow Ventures; Q1 FY26 revenue Rs 197 Cr (+38% YoY), EBITDA loss Rs 63 Cr (vs Rs 46 Cr prior year)
A3: TIGC FY25 financials | B3: Entrackr, 15 Jan 2026, sourced from RoC filings - revenue Rs 204 Cr (+101%), net loss Rs 23 Cr (from Rs 5 Cr profit), EBITDA margin -6.37%
A4: Bewakoof FY25 financials | B4: Inc42, 31 Oct 2025 & Entrackr, 31 Oct 2025, sourced from RoC filings - revenue Rs 173 Cr (+8%), net loss Rs 73.2 Cr (-29% YoY), EBITDA margin -34%
A5: Wrogn FY25 financials | B5: Inc42 & Entrackr, 25 Sep 2025, sourced from RoC filings - revenue Rs 223.2 Cr (-9%), net loss Rs 75.5 Cr (+32% YoY), accumulated losses Rs 709 Cr
A6: Nobero | B6: ECDB e-commerce tracker (estimate, not audited) - ~$60M GMV in 2025, +75-80% YoY; no RoC filing located
A7: TMRW brand portfolio | B7: Inc42, 31 Oct 2025 - TMRW operates 16 stores across 7 cities as of FY25; Bewakoof, TIGC and Nobero all expanded into physical retail during the year
