Workbook

Sheet Summary
B2: TMRW House of Brands — Portfolio Profitability Diagnostic (v2)
B3: Rebuilt on primary sources: ABFRL/ABLBL Q4 FY25 PR, Motilal Oswal 23-Sep-25, ABFRL SE intimation 17-Sep-26, AGM Speech, Q3 FY26 Investor Presentation
B5: The Problem — Updated
B6: TMRW's brand-level FY25 filings (year ended Mar 2025) still show a genuine spread in performance: TIGC scaling profitably, Bewakoof improving margin through cost discipline, and Wrogn losing revenue while ad spend rose. But the more recent Q3 FY26 investor presentation (Oct-Dec 2025) shows the TMRW group overall has since inflected: EBITDA margin improved ~900bps YoY and management states "TMRW losses now peaked." This diagnostic keeps the FY25 brand-level classification (the best granularity available) but adds that group-level trajectory as essential context.
B11: Portfolio 2x2: Growth vs. Profitability Trend (FY25 vs FY24)
B12: Brand | C12: Revenue Growth YoY | D12: EBITDA Margin (FY25) | E12: Net Loss Trend YoY | F12: Classification
B13: The Indian Garage Co (TIGC) | C13: ='Brand Financials'!E6 -> 1.0118227 | D13: ='Brand Financials'!F6 -> -0.0637 | E13: Profit -> Loss (+Rs5cr to -Rs23cr) | F13: Scale
B14: Bewakoof | C14: ='Brand Financials'!E12 -> 0.075201989 | D14: ='Brand Financials'!F12 -> -0.34 | E14: ='Brand Financials'!I12 -> 0.2900097 | F14: Fix
B15: Wrogn | C15: ='Brand Financials'!E18 -> -0.090093763 | D15: ='Brand Financials'!F18 -> -0.275 | E15: ='Brand Financials'!I18 -> -0.32922535 | F15: Cut / Harvest
B16: Nobero* | C16: n/a (1 yr only) | D16: n/a (not disclosed) | E16: n/a | F16: Watch (data-limited)
B17: Urbano** | C17: +53.2% (FY25->FY26) | D17: n/a (not disclosed) | E17: n/a | F17: Watch (data-limited)
B19: *Nobero: FY25 revenue Rs 133.5cr now confirmed via Motilal Oswal (company-sourced), replacing an earlier unreliable GMV estimate — but no margin or prior-year figure is disclosed, so it still can't be classified. **Urbano: revenue growth accelerating (+16.7% FY24->FY25, +53.2% FY25->FY26); ABDFVL moved to 100% ownership on 17-Sep-2026. No EBITDA margin disclosed yet.
B22: TMRW Group Trajectory (context, not brand-level)
B23: Q3 FY25 -> Q3 FY26: TMRW's official segment EBITDA margin improved from -33.0% to -23.7%, roughly 900bps YoY, on 29% ex-Wrogn revenue growth. Management describes this as losses having "now peaked." See the TMRW Trajectory tab for the full quarterly series and the Recommendation Model tab for how this affects the Wrogn call.
B27: Headline Recommendation
B28: 1) SCALE — TIGC: revenue doubled (+101%) with the best EBITDA margin in the portfolio (-6.4%). Deserves the next round of marketing and offline capex. 2) FIX — Bewakoof: revenue nearly flat (+8%) but losses fell 29% purely from cost discipline. Hold spend, keep tightening opex. 3) CUT/HARVEST, WITH A CAVEAT — Wrogn: FY25 showed a 2nd straight year of revenue decline (-9%) with losses growing 32% and ad spend up 63% without a sales response. That evidence still stands. But TMRW's Q3 FY26 group-level margin has since improved ~900bps — Wrogn's own FY26 numbers are not separately disclosed, so recommend requesting Wrogn-specific FY26 data before finalizing any spend freeze, rather than acting on FY25 data alone. 4) WATCH — Nobero & Urbano: both now have real (non-GMV) revenue figures, but neither discloses a margin. Urbano's growth is accelerating and ABFRL just took it to 100% ownership — worth a dedicated diagnostic once its P&L is available.

Sheet Brand Financials
A1: Brand-Level Financials — FY24 vs FY25 (Rs Crore)
A3: Brand | C3: Revenue FY24 | D3: Revenue FY25 | E3: Growth YoY | F3: EBITDA Margin FY25 | G3: Net Loss FY24 | H3: Net Loss FY25 | I3: Loss Change YoY | K3: Source
A6: The Indian Garage Co (TIGC) | C6: 101.5 | D6: 204.2 | E6: =(D6-C6)/C6 -> 1.0118227 | F6: -0.0637 | G6: 5 | H6: -23 | I6: =(H6-G6)/ABS(G6) -> -5.6 | K6: Entrackr 15-Jan-26 (RoC filing); revenue cross-checked vs Motilal Oswal 23-Sep-25 (INR 2042m). Flipped Rs 5cr profit -> Rs 23cr loss as material costs +142%, job-work +193%
A12: Bewakoof | C12: 160.9 | D12: 173 | E12: =(D12-C12)/C12 -> 0.075201989 | F12: -0.34 | G12: -103.1 | H12: -73.2 | I12: =(H12-G12)/ABS(G12) -> 0.2900097 | K12: Inc42 31-Oct-25 (RoC filing); cross-checked vs Motilal Oswal (INR 1730m). EBITDA loss improved 38% to Rs 57cr; ad spend flat at Rs 48.6cr
A18: Wrogn | C18: 245.3 | D18: 223.2 | E18: =(D18-C18)/C18 -> -0.090093763 | F18: -0.275 | G18: -56.8 | H18: -75.5 | I18: =(H18-G18)/ABS(G18) -> -0.32922535 | K18: Inc42/Entrackr 25-Sep-25 (RoC filing). Total income incl. other income Rs 232.3cr per Motilal Oswal (INR 2323m). Ad spend +63% YoY despite falling sales; accumulated losses Rs 709cr
A24: Nobero | C24: n/a | D24: 133.5 | E24: n/a | F24: n/a | G24: n/a | H24: n/a | I24: n/a | K24: Motilal Oswal 23-Sep-25 (INR 1335m), company-sourced. REPLACES an earlier unreliable GMV-tracker estimate of ~Rs 500cr. No FY24 comparison or margin disclosed.
A30: Urbano (FY25 shown; see Trajectory tab for 3yr) | C30: 66.78 | D30: 77.93 | E30: =(D30-C30)/C30 -> 0.16696616 | F30: n/a | G30: n/a | H30: n/a | I30: n/a | K30: ABFRL SE intimation 17-Sep-26, Annexure A. FY26 revenue Rs 119.38cr (+53.2% YoY) — see 'Urbano Trend' tab. ABDFVL raised stake 84.38% -> 100% same day.
A36: TMRW consolidated (segment-reported): see 'TMRW Trajectory' tab for the full quarterly series and sourcing.

Sheet 2x2 Scoring
A1: Classification Logic
A3: Axis 1: Revenue growth YoY (FY25 vs FY24). Axis 2: EBITDA margin (FY25). Rule-based split, appropriate for 3 comparable data points — Nobero and Urbano are excluded (no disclosed margin).
A6: Brand | B6: Revenue Growth YoY | C6: EBITDA Margin FY25 | D6: Quadrant | E6: Rationale
A7: The Indian Garage Co | B7: ='Brand Financials'!E6 -> 1.0118227 | C7: ='Brand Financials'!F6 -> -0.0637 | D7: Scale | E7: Highest growth (+101%) + best portfolio margin (-6.4%) = closest to profitable scale
A8: Bewakoof | B8: ='Brand Financials'!E12 -> 0.075201989 | C8: ='Brand Financials'!F12 -> -0.34 | D8: Fix | E8: Modest growth (+8%) but margin improved 2,500 bps YoY via cost control — protect it, don't overspend yet
A9: Wrogn | B9: ='Brand Financials'!E18 -> -0.090093763 | C9: ='Brand Financials'!F18 -> -0.275 | D9: Cut / Harvest | E9: Revenue down 2 years running, losses widening, ad spend +63% without a sales response — FY25 evidence; group-level TMRW has since improved (see Recommendation tab)

Sheet TMRW Trajectory
A1: TMRW Group Trajectory — Is the Loss Actually Peaking?
A3: Official segment-reported figures from the Q3 FY26 Investor Presentation. Revenue growth figures are stated ex-Wrogn by the company; EBITDA and margin are as reported in the segmental table.
A7: Period | B7: Revenue (Rs Cr) | C7: EBITDA (Rs Cr) | D7: EBITDA Margin | E7: Note
A8: Q3 FY25 | B8: 187 | C8: -62 | D8: -0.33 | E8: Base quarter
A9: Q3 FY26 | B9: 242 | C9: -57 | D9: -0.237 | E9: +29% YoY revenue (ex-Wrogn); margin +~900bps YoY; mgmt: "TMRW losses now peaked"
A10: 9M FY25 | B10: 506 | C10: -146 | D10: -0.289 | E10: Base period
A11: 9M FY26 | B11: 662 | C11: -182 | D11: -0.275 | E11: +31% YoY revenue (ex-Wrogn)
A13: Margin improvement, Q3 FY25 -> Q3 FY26 (percentage points) | C13: =(D9-D8)*100 -> 9.3
A15: Reading this: the brand-level classification on the Summary/2x2 tabs is built on FY25 annual data because that is the only granularity with individual-brand margins. This tab is the group-level counterpart — it shows TMRW as a whole is executing a turnaround since FY25, even though we cannot yet confirm whether Wrogn specifically is participating in that improvement.

Sheet Urbano Trend
A1: Urbano — 3-Year Revenue Trend
A3: Urbano is owned via Imperial Online Services Pvt Ltd. ABFRL's subsidiary ABDFVL increased its stake from 84.38% to 100% on 17-Sep-2026, making Imperial a wholly-owned step-down subsidiary. No EBITDA margin is disclosed for Urbano, so it cannot be placed on the 2x2 classification yet.
A7: Fiscal Year | B7: Revenue (Rs Cr) | C7: Growth YoY | D7: Note
A8: FY24 | B8: 66.78 | D8: Source: ABFRL SE intimation, 17-Sep-2026, Annexure A (RoC-sourced 3-yr history)
A9: FY25 | B9: 77.93 | C9: =(B9-B8)/B8 -> 0.16696616
A10: FY26 | B10: 119.38 | C10: =(B10-B9)/B9 -> 0.53188759
A12: Growth is accelerating: +16.7% (FY24->FY25) then +53.2% (FY25->FY26) — worth a dedicated diagnostic once profitability data is disclosed.

Sheet Recommendation Model
A1: Scenario: Reallocate Wrogn's Incremental Ad Spend to TIGC
A3: Wrogn's FY25 ad/promo spend rose 63% YoY while revenue fell 9% — that spend did not convert. TIGC's EBITDA margin (-6.4%) is closest to breakeven in the portfolio. This scenario models freezing Wrogn's incremental FY25 spend and redeploying it into TIGC, holding TIGC's FY25 margin constant. IMPORTANT CAVEAT: TMRW's group-level margin has since improved ~900bps (Q3 FY26 vs Q3 FY25) — Wrogn's own FY26 performance is not separately disclosed, so treat this as a scenario built on the last confirmed Wrogn-specific data, not a current recommendation to execute today.
A9: Key Assumptions (editable — blue cells on yellow fill)
A10: Wrogn FY25 ad/promo spend (Rs Cr) | B10: 65 | D10: Consistent with Entrackr's reported +63% YoY increase
A11: Wrogn FY24 ad/promo spend (Rs Cr) | B11: 40 | D11: Implied base before the 63% YoY increase
A12: TIGC revenue generated per Rs 1 of incremental ad spend (assumed) | B12: 8 | D12: Placeholder — TIGC's ad spend isn't separately disclosed; assumes efficiency consistent with its FY25 revenue-doubling. State as an assumption when presenting.
A13: TIGC FY25 EBITDA margin | B13: -0.0637 | D13: From Brand Financials tab
A16: Reallocatable spend | B16: =B10-B11 -> 25
A18: Projected Impact
A19: Incremental TIGC revenue from reallocated spend (Rs Cr) | B19: =B16*B12 -> 200
A20: Incremental TIGC EBITDA impact (Rs Cr) | B20: =B19*B13 -> -12.74
A21: Wrogn EBITDA impact of freezing incremental spend (Rs Cr; spend removed = loss avoided 1:1) | B21: =B16 -> 25
A22: Net portfolio EBITDA improvement vs. FY25 base (Rs Cr) | B22: =B20+B21 -> 12.26
A24: Read: this is a directional model on FY25 data, not a current recommendation. Before executing, confirm (a) TIGC's actual ad-spend efficiency, not the assumption used here, and (b) Wrogn's FY26 revenue and margin trend specifically, since the group-level TMRW recovery could mean Wrogn's individual picture has already changed since this evidence was filed.

Sheet Sources
A1: Source | B1: Detail
A2: ABFRL/ABLBL Q4 FY25 Results PR | B2: 23 May 2025 — Demerged ABFRL Q4 FY25: revenue Rs1719cr (+9%), EBITDA Rs295cr (+202%); FY25 full year revenue Rs7355cr (+14%), EBITDA Rs854cr (+64%); TMRW portfolio +27% YoY in Q4, 16 stores
A3: Motilal Oswal Institutional Equities | B3: 23 Sep 2025 — Brand-level revenue/valuation table (Exhibit 5) sourced from Company data: TIGC, Bewakoof, Wrogn, Nobero, Urbano, others; TMRW segment financial projections FY23-28E
A4: ABFRL SE Intimation re: Imperial/Urbano | B4: 17 Sep 2026 — ABDFVL increased stake in Imperial Online Services (Urbano brand) from 84.38% to 100%; 3-year revenue history Rs66.78cr/77.93cr/119.38cr (FY24/25/26)
A5: ABFRL AGM Chairman's Speech | B5: FY26 — ABFRL consolidated revenue Rs8177cr (+11% YoY); TMRW +34% revenue growth, 120 stores; Ethnic revenue Rs2227cr (+14%), margin +560bps to 10.8%
A6: ABFRL Q3 FY26 Investor Presentation | B6: Board meeting 5 Feb 2026 — Q3 FY26 segmental: TMRW revenue Rs242cr (+29% YoY ex-Wrogn), EBITDA -Rs57cr, margin -23.7% (vs -33.0% Q3FY25); ABFRL consolidated Rs2374cr (+8%), EBITDA Rs370cr (+13%)
A7: Inc42 / Entrackr (RoC filings) | B7: TIGC (15 Jan 2026), Bewakoof (31 Oct 2025), Wrogn (25 Sep 2025) — brand-level FY24/FY25 P&L, retained as the finest-grain source for individual-brand classification
